{"id":"6683957f2e516f6146af483d","typeName":"IronSight","category":"mod_scope","parentTypeChain":["IronSight","Sights","FunctionalMod","Mod","CompoundItem","Item"],"handbook":{"categoryId":null,"price":0},"common":{"name":{"zh":"爱国者提把","en":"Patriot rear sight carry handle"},"shortName":{"zh":"爱国者 RS","en":"Patriot RS"},"description":{"zh":"爱国者可拆卸提把，带AR-15照门。","en":"Patriotic detachable carry handle with a rear sight for the AR-15."},"weight":0.15,"width":1,"height":1,"rarity":"Not_exist","backgroundColor":"blue"},"properties":{"_raw":{"Accuracy":0,"AdjustableOpticSensitivity":0,"AdjustableOpticSensitivityMax":0,"AimSensitivity":[[0.65]],"AnimationVariantsNumber":0,"BackgroundColor":"blue","BlocksCollapsible":false,"BlocksFolding":false,"CalibrationDistances":[[100]],"CanPutIntoDuringTheRaid":true,"CanRequireOnRagfair":false,"CanSellOnRagfair":true,"CantRemoveFromSlotsDuringRaid":[],"ConflictingItems":["57ac965c24597706be5f975c","57aca93d2459771f2c7e26db","544a3f024bdc2d1d388b4568","544a3a774bdc2d3a388b4567","5d2dc3e548f035404a1a4798","57adff4f24597737f373b6e6","5c0517910db83400232ffee5","591c4efa86f7741030027726","570fd79bd2720bc7458b4583","570fd6c2d2720bc6458b457f","558022b54bdc2dac148b458d","5c07dd120db834001c39092d","5c0a2cec0db834001b7ce47d","58491f3324597764bc48fa02","584924ec24597768f12ae244","5b30b0dc5acfc400153b7124","6165ac8c290d254f5e6b2f6c","60a23797a37c940de7062d02","5d2da1e948f035477b1ce2ba","5c0505e00db834001b735073","609a63b6e2ff132951242d09","584984812459776a704a82a6","59f9d81586f7744c7506ee62","570fd721d2720bc5458b4596","57ae0171245977343c27bfcf","5dfe6104585a0c3e995c7b82","544a3d0a4bdc2d1b388b4567","5d1b5e94d7ad1a2b865a96b0","609bab8b455afd752b2e6138","58d39d3d86f77445bb794ae7","616554fe50224f204c1da2aa","5c7d55f52e221644f31bff6a","616584766ef05c2ce828ef57","5b3b6dc75acfc47a8773fb1e","615d8d878004cc50514c3233","5b2389515acfc4771e1be0c0","577d128124597739d65d0e56","618b9643526131765025ab35","618bab21526131765025ab3f","5c86592b2e2216000e69e77c","5a37ca54c4a282000d72296a","5d0a29fed7ad1a002769ad08","5c064c400db834001d23f468","58d2664f86f7747fec5834f6","57c69dd424597774c03b7bbc","5b3b99265acfc4704b4a1afb","5aa66a9be5b5b0214e506e89","5aa66c72e5b5b00016327c93","5c1cdd302e221602b3137250","61714b2467085e45ef140b2c","6171407e50224f204c1da3c5","61713cc4d8e3106d9806c109","5b31163c5acfc400153b71cb","5a33b652c4a28232996e407c","5a33b2c9c4a282000c5a9511","59db7eed86f77461f8380365","5a1ead28fcdbcb001912fa9f","5dff77c759400025ea5150cf","626bb8532c923541184624b4","62811f461d5df4475f46a332","63fc449f5bd61c6cf3784a88","6477772ea8a38bb2050ed4db","6478641c19d732620e045e17","64785e7c19d732620e045e15","65392f611406374f82152ba5","653931da5db71d30ab1d6296","655f13e0a246670fb0373245","6567e751a715f85433025998","6761759e7ee06333f108bf86","67641a851b2899700609901a","03f6c86c56945862820e1006","682be7bf16812803987c3715","5ae3d18efa17cbd51e898ced"],"CustomAimPlane":"","Description":"sight_rear_ar15_colt_carry_hande_std","DiscardLimit":-1,"DiscardingBlock":false,"DoubleActionAccuracyPenaltyMult":1,"DropSoundType":"None","Durability":100,"EffectiveDistance":0,"Ergonomics":0,"ExamineExperience":2,"ExamineTime":1,"ExaminedByDefault":true,"ExtraSizeDown":0,"ExtraSizeForceAdd":false,"ExtraSizeLeft":0,"ExtraSizeRight":0,"ExtraSizeUp":0,"ForbidMissingVitalParts":false,"ForbidNonEmptyContainers":false,"Grids":[],"HasShoulderContact":false,"Height":1,"HideEntrails":false,"InsuranceDisabled":false,"IsAdjustableOptic":false,"IsAlwaysAvailableForInsurance":false,"IsAnimated":false,"IsLockedafterEquip":false,"IsSecretExitRequirement":false,"IsSpecialSlotOnly":false,"IsUnbuyable":false,"IsUndiscardable":false,"IsUngivable":false,"IsUnremovable":false,"IsUnsaleable":false,"ItemSound":"mod","LeftHandItem":false,"LootExperience":5,"Loudness":0,"MergesWithChildren":true,"MetascoreGroup":"Firepower","MinMaxFov":{"x":0,"y":0,"z":0},"ModesCount":[1],"Name":"sight_rear_ar15_colt_carry_hande_std","NotShownInSlot":false,"Prefab":{"path":"WeaponPatriot/patriotcarryhandle.bundle","rcid":""},"QuestItem":false,"QuestStashMaxCount":0,"RagFairCommissionModifier":1,"RaidModdable":true,"RarityPvE":"Not_exist","Recoil":0,"RepairCost":0,"RepairSpeed":0,"ScopesCount":1,"ShortName":"sight_rear_ar15_colt_carry_hande_std","SightingRange":600,"Slots":[{"_id":"5ae9c31e5acfc4039d663545","_mergeSlotWithChildren":false,"_name":"mod_scope","_parent":"5ae30bad5acfc400185c2dc4","_props":{"filters":[{"Filter":["5c1cdd512e22161b267d91ae","5c05293e0db83400232fff80","5c052a900db834001a66acbd","59db7e1086f77448be30ddf3"],"Shift":0}]},"_proto":"55d30c4c4bdc2db4468b457e","_required":false}],"StackMaxSize":1,"StackObjectsCount":1,"ToolModdable":false,"UniqueAnimationModID":0,"Unlootable":false,"UnlootableFromSide":[],"UnlootableFromSlot":"FirstPrimaryWeapon","UsePrefab":{"path":"","rcid":""},"Velocity":0,"Weight":0.15,"Width":1,"ZoomSensitivity":0,"Zooms":[[1]],"sightModType":"iron"},"mod":{"ergonomics":0,"recoilForceUp":0,"recoilForceBack":0,"accuracy":0,"loudness":0,"effectiveDistance":0,"zooms":"1x","sightingRange":600,"sightModType":"iron","calibrationDistances":[100],"velocity":0,"muzzleModType":"","malfunctionChance":0,"loadUnloadModifier":0,"checkTimeModifier":0,"foldable":false,"retractable":false},"resolvedConflicts":[{"id":"57ac965c24597706be5f975c","name":{"zh":"ELCAN SpecterDR 1x/4x瞄准镜","en":"ELCAN SpecterDR 1x/4x scope"},"isWikiItem":true},{"id":"57aca93d2459771f2c7e26db","name":{"zh":"ELCAN SpecterDR 1x/4x瞄准镜 FDE","en":"ELCAN SpecterDR 1x/4x scope (FDE)"},"isWikiItem":true},{"id":"544a3f024bdc2d1d388b4568","name":{"zh":"ELCAN Specter OS4x突击瞄准镜","en":"ELCAN Specter OS4x assault scope"},"isWikiItem":true},{"id":"544a3a774bdc2d3a388b4567","name":{"zh":"勒波德 Mark 4 HAMR 4x24 DeltaPoint混合式突击瞄准镜","en":"Leupold Mark 4 HAMR 4x24 DeltaPoint hybrid assault scope"},"isWikiItem":true},{"id":"5d2dc3e548f035404a1a4798","name":{"zh":"Monstrum 紧凑战术棱镜式瞄准镜 2x32","en":"Monstrum Tactical Compact Prism Scope 2x32"},"isWikiItem":true},{"id":"57adff4f24597737f373b6e6","name":{"zh":"Sig BRAVO4 4X30瞄准镜","en":"SIG Sauer BRAVO4 4x30 scope"},"isWikiItem":true},{"id":"5c0517910db83400232ffee5","name":{"zh":"Valday PS-320 1x/6x瞄准镜","en":"Valday PS-320 1/6x scope"},"isWikiItem":true},{"id":"591c4efa86f7741030027726","name":{"zh":"Axion Kobra EKP-8-18 反射式瞄具","en":"Axion Kobra EKP-8-18 reflex sight"},"isWikiItem":true},{"id":"570fd79bd2720bc7458b4583","name":{"zh":"OKP-7反射式瞄具","en":"OKP-7 reflex sight"},"isWikiItem":true},{"id":"570fd6c2d2720bc6458b457f","name":{"zh":"Eotech 553全息瞄具","en":"EOTech 553 holographic sight"},"isWikiItem":true},{"id":"558022b54bdc2dac148b458d","name":{"zh":"EOTech EXPS3-0 全息瞄具（黄褐色）","en":"EOTech EXPS3-0 holographic sight (Tan)"},"isWikiItem":true},{"id":"5c07dd120db834001c39092d","name":{"zh":"EOTech HHS-1 复合瞄具","en":"EOTech HHS-1 hybrid sight"},"isWikiItem":true},{"id":"5c0a2cec0db834001b7ce47d","name":{"zh":"EOTech HHS-1 复合瞄具（黄褐色）","en":"EOTech HHS-1 hybrid sight (Tan)"},"isWikiItem":true},{"id":"58491f3324597764bc48fa02","name":{"zh":"EOTech XPS3-0 全息瞄具","en":"EOTech XPS3-0 holographic sight"},"isWikiItem":true},{"id":"584924ec24597768f12ae244","name":{"zh":"EOTech XPS3-2 全息瞄具","en":"EOTech XPS3-2 holographic sight"},"isWikiItem":true},{"id":"5b30b0dc5acfc400153b7124","name":{"zh":"Holosun HS401G5反射式瞄具","en":"Holosun HS401G5 reflex sight"},"isWikiItem":true},{"id":"6165ac8c290d254f5e6b2f6c","name":{"zh":"Leapers UTG反射式瞄具","en":"Leapers UTG reflex sight"},"isWikiItem":true},{"id":"60a23797a37c940de7062d02","name":{"zh":"SIG Romeo 8T反射式瞄具","en":"SIG Sauer ROMEO8T reflex sight"},"isWikiItem":true},{"id":"5d2da1e948f035477b1ce2ba","name":{"zh":"Trijicon SRS-02反射式瞄具","en":"Trijicon SRS-02 reflex sight"},"isWikiItem":true},{"id":"5c0505e00db834001b735073","name":{"zh":"Valday PK-120 (1P87) 反射式瞄具","en":"Valday PK-120 (1P87) reflex sight"},"isWikiItem":true},{"id":"609a63b6e2ff132951242d09","name":{"zh":"Krechet反射式瞄具","en":"Valday Krechet reflex sight"},"isWikiItem":true},{"id":"584984812459776a704a82a6","name":{"zh":"VOMZ Pilad P1X42 \"WEAVER\"反射式瞄具","en":"VOMZ Pilad P1x42 Weaver reflex sight"},"isWikiItem":true},{"id":"59f9d81586f7744c7506ee62","name":{"zh":"Vortex Razor AMG UH-1全息瞄具","en":"Vortex Razor AMG UH-1 holographic sight"},"isWikiItem":true},{"id":"570fd721d2720bc5458b4596","name":{"zh":"Walther MRS反射式瞄具","en":"Walther MRS reflex sight"},"isWikiItem":true},{"id":"57ae0171245977343c27bfcf","name":{"zh":"Belomo PK-06反射式瞄具","en":"BelOMO PK-06 reflex sight"},"isWikiItem":true},{"id":"5dfe6104585a0c3e995c7b82","name":{"zh":"NcSTAR ADO P4 Sniper 3-9x42步枪瞄准镜","en":"NcSTAR ADO P4 Sniper 3-9x42 riflescope"},"isWikiItem":true},{"id":"544a3d0a4bdc2d1b388b4567","name":{"zh":"Nightforce NXS 2.5-10x24瞄准镜","en":"Nightforce NXS 2.5-10x24 scope"},"isWikiItem":true},{"id":"5d1b5e94d7ad1a2b865a96b0","name":{"zh":"FLIR RS-32 2.25-9x 35毫米 60Hz热成像步枪瞄准镜","en":"FLIR RS-32 2.25-9x 35mm 60Hz thermal riflescope"},"isWikiItem":true},{"id":"609bab8b455afd752b2e6138","name":{"zh":"Torrey Pines Logic T12W热成像反射式瞄具","en":"Torrey Pines Logic T12W 30Hz thermal reflex sight"},"isWikiItem":true},{"id":"58d39d3d86f77445bb794ae7","name":{"zh":"Aimpoint Micro瞄具基座","en":"Aimpoint Micro Standard Mount"},"isWikiItem":true},{"id":"616554fe50224f204c1da2aa","name":{"zh":"Aimpoint Micro H-2瞄具基座","en":"Aimpoint Micro H-2 Standard Mount"},"isWikiItem":true},{"id":"5c7d55f52e221644f31bff6a","name":{"zh":"Aimpoint LRP COMP M4瞄具基座","en":"Aimpoint CompM4/PRO LRP mount"},"isWikiItem":true},{"id":"616584766ef05c2ce828ef57","name":{"zh":"Aimpoint QRP2 CompM4/PRO反射式瞄具基座","en":"Aimpoint CompM4/PRO QRP2 mount"},"isWikiItem":true},{"id":"5b3b6dc75acfc47a8773fb1e","name":{"zh":"Armasight Vulcan 通用基座","en":"Armasight Vulcan universal base"},"isWikiItem":true},{"id":"615d8d878004cc50514c3233","name":{"zh":"B&T QD NAR Aimpoint ACRO 准镜基座","en":"B&T QD NAR mount for Aimpoint ACRO"},"isWikiItem":true},{"id":"5b2389515acfc4771e1be0c0","name":{"zh":"Burris AR- P.E.P.R. 30毫米环形基座","en":"Burris AR-P.E.P.R. 30mm ring scope mount"},"isWikiItem":true},{"id":"577d128124597739d65d0e56","name":{"zh":"Burris FastFire韦弗式基座","en":"Burris FastFire Weaver Base"},"isWikiItem":true},{"id":"618b9643526131765025ab35","name":{"zh":"Geissele Super Precision 30毫米环形基座","en":"Geissele Super Precision 30mm ring scope mount"},"isWikiItem":true},{"id":"618bab21526131765025ab3f","name":{"zh":"Geissele Super Precision 30毫米环形基座 （DDC）","en":"Geissele Super Precision 30mm ring scope mount (DDC)"},"isWikiItem":true},{"id":"5c86592b2e2216000e69e77c","name":{"zh":"I-E-A Mil Optics Magmount 34毫米一体式基座环","en":"IEA Mil-Optics KH/F 34mm one-piece magmount"},"isWikiItem":true},{"id":"5a37ca54c4a282000d72296a","name":{"zh":"JP 30毫米环形基座","en":"JP Enterprises Flat-Top 30mm ring scope mount"},"isWikiItem":true},{"id":"5d0a29fed7ad1a002769ad08","name":{"zh":"KMZ 1P69 Weaver基座","en":"KMZ 1P69 Weaver mount"},"isWikiItem":true},{"id":"5c064c400db834001d23f468","name":{"zh":"La Rue Tactical QD LT-101皮卡汀尼立管导轨基座","en":"LaRue LT101 QD Tactical Picatinny Riser mount"},"isWikiItem":true},{"id":"58d2664f86f7747fec5834f6","name":{"zh":"Cross Slot Deltapoint瞄具基座","en":"DeltaPoint Cross Slot Mount base"},"isWikiItem":true},{"id":"57c69dd424597774c03b7bbc","name":{"zh":"Lobar Arms 30毫米瞄准镜基座","en":"Lobaev Arms 30mm scope mount"},"isWikiItem":true},{"id":"5b3b99265acfc4704b4a1afb","name":{"zh":"Nightforce 30毫米瞄准镜基座环","en":"Nightforce Magmount 30mm ring scope mount"},"isWikiItem":true},{"id":"5aa66a9be5b5b0214e506e89","name":{"zh":"Nightforce MagMount一体式基座环","en":"Nightforce Magmount 34mm ring scope mount"},"isWikiItem":true},{"id":"5aa66c72e5b5b00016327c93","name":{"zh":"Nightforce MagMount Multimount 34毫米一体式导轨基座","en":"Nightforce Magmount 34mm ring scope mount with Ruggedized Accessory Platform"},"isWikiItem":true},{"id":"5c1cdd302e221602b3137250","name":{"zh":"Kiba Arms Short Mount瞄准镜转接器","en":"Kiba Arms Short Mount sight adapter"},"isWikiItem":true},{"id":"61714b2467085e45ef140b2c","name":{"zh":"Recknagel Era-Tac Sunshade Aimpoint T-1基座","en":"Recknagel Era-Tac Sunshade mount for Aimpoint T-1 sights"},"isWikiItem":true},{"id":"6171407e50224f204c1da3c5","name":{"zh":"Recknagel Era-Tac 30毫米环形基座","en":"Recknagel Era-Tac 30mm ring scope mount"},"isWikiItem":true},{"id":"61713cc4d8e3106d9806c109","name":{"zh":"Recknagel Era-Tac 34毫米环形基座","en":"Recknagel Era-Tac 34mm ring scope mount"},"isWikiItem":true},{"id":"5b31163c5acfc400153b71cb","name":{"zh":"西格-绍尔Romeo系列瞄具基座","en":"SIG Sauer ROMEO sight mount"},"isWikiItem":true},{"id":"5a33b652c4a28232996e407c","name":{"zh":"Trijicon RMR高轮廓型基座","en":"Trijicon RMR high profile mount"},"isWikiItem":true},{"id":"5a33b2c9c4a282000c5a9511","name":{"zh":"Trijicon RMR低轮廓型基座","en":"Trijicon RMR low profile mount"},"isWikiItem":true},{"id":"59db7eed86f77461f8380365","name":{"zh":"TA51瞄具基座","en":"Trijicon TA51 sight mount"},"isWikiItem":true},{"id":"5a1ead28fcdbcb001912fa9f","name":{"zh":"UNV DLOC-IRD瞄准镜基座","en":"UNV DLOC-IRD sight mount"},"isWikiItem":true},{"id":"5dff77c759400025ea5150cf","name":{"zh":"UTG 25毫米环","en":"Leapers UTG 25mm ring scope mount"},"isWikiItem":true},{"id":"626bb8532c923541184624b4","name":{"zh":"SwampFox Trihawk Prism瞄准镜3x30","en":"SwampFox Trihawk Prism Scope 3x30"},"isWikiItem":true},{"id":"62811f461d5df4475f46a332","name":{"zh":"AI AX-50 34毫米瞄具基座","en":"AI AX-50 34mm scope mount"},"isWikiItem":true},{"id":"63fc449f5bd61c6cf3784a88","name":{"zh":"Armasight Zeus通用基座","en":"Armasight Zeus universal base"},"isWikiItem":true},{"id":"6477772ea8a38bb2050ed4db","name":{"zh":"SIG Sauer ROMEO7 1x30反射式瞄具（原型版本）","en":"SIG Sauer ROMEO7 1x30 reflex sight (Prototype)"},"isWikiItem":true},{"id":"6478641c19d732620e045e17","name":{"zh":"SIG Sauer ECHO1 1-2x30毫米 30赫兹反射式热成像瞄准镜","en":"SIG Sauer ECHO1 1-2x30mm 30Hz thermal reflex scope"},"isWikiItem":true},{"id":"64785e7c19d732620e045e15","name":{"zh":"ELCAN Specter HCO全息瞄准镜","en":"ELCAN Specter HCO holographic sight"},"isWikiItem":true},{"id":"65392f611406374f82152ba5","name":{"zh":"GBRS Aimpoint Hydra基座套组（黑色）","en":"GBRS Aimpoint Hydra Mount Kit (Black)"},"isWikiItem":true},{"id":"653931da5db71d30ab1d6296","name":{"zh":"GBRS Aimpoint Hydra基座套组（FDE）","en":"GBRS Aimpoint Hydra Mount Kit (FDE)"},"isWikiItem":true},{"id":"655f13e0a246670fb0373245","name":{"zh":"Wilcox BOSS Xe反射式瞄具","en":"Wilcox BOSS Xe reflex sight"},"isWikiItem":true},{"id":"6567e751a715f85433025998","name":{"zh":"SIG ALPHA4 30环形瞄具基座","en":"SIG Sauer ALPHA4 30mm ring scope mount"},"isWikiItem":true},{"id":"6761759e7ee06333f108bf86","name":{"zh":"Leupold Mark IMS 35毫米瞄准镜固定基座","en":"Leupold Mark IMS 35mm ring scope mount"},"isWikiItem":true},{"id":"67641a851b2899700609901a","name":{"zh":"Cyclone Shakhin 基座","en":"Cyclone Shakhin mount"},"isWikiItem":true},{"id":"03f6c86c56945862820e1006","name":{"zh":"Aimpoint CS 反射式瞄准镜","en":"Aimpoint CS reflex sight"},"isWikiItem":true},{"id":"682be7bf16812803987c3715","name":{"zh":"Aimpoint CGA5P 2倍伸缩式瞄准镜（带提把）","en":"Aimpoint CGA5P 2x telescopic sight with carryhandle"},"isWikiItem":true},{"id":"5ae3d18efa17cbd51e898ced","name":{"zh":"ITL MARS反射式瞄准镜","en":"ITL MARS reflex sight"},"isWikiItem":true}]},"slots":[{"name":"mod_scope","id":"5ae9c31e5acfc4039d663545","required":false,"filter":["5c1cdd512e22161b267d91ae","5c05293e0db83400232fff80","5c052a900db834001a66acbd","59db7e1086f77448be30ddf3"]}],"image":null,"isMod":true}